setup.py
Flask_thridy.egg-info/PKG-INFO
Flask_thridy.egg-info/SOURCES.txt
Flask_thridy.egg-info/dependency_links.txt
Flask_thridy.egg-info/not-zip-safe
Flask_thridy.egg-info/requires.txt
Flask_thridy.egg-info/top_level.txt
flask_thridy/__init__.py
flask_thridy/error.py
flask_thridy/sina.py
flask_thridy/tecent.py
flask_thridy/wechat.py