Metadata-Version: 1.1
Name: Flask-thridy
Version: 0.0.2
Summary: simple use thridy for login you web
Home-page: https://github.com/Feeeenng/flask-thridy
Author: Feeeenng
Author-email: z332007851@163.com
License: BSD
Platform: a
Platform: n
Platform: y
Classifier: Environment :: Web Environment
Classifier: Framework :: Flask
Classifier: Operating System :: OS Independent
Classifier: Programming Language :: Python :: 2.7
Classifier: Intended Audience :: Developers
Classifier: License :: OSI Approved :: BSD License
Classifier: Topic :: Internet :: WWW/HTTP :: Dynamic Content
Classifier: Topic :: Software Development :: Libraries :: Python Modules
